sanic_amqp/__init__.py
sanic_amqp-0.2.0.dist-info/LICENSE
sanic_amqp-0.2.0.dist-info/METADATA
sanic_amqp-0.2.0.dist-info/WHEEL
sanic_amqp-0.2.0.dist-info/top_level.txt
sanic_amqp-0.2.0.dist-info/RECORD
