Metadata-Version: 2.1
Name: sanic-amqp
Version: 0.2.0
Summary: AMQP support for Sanic framework
Home-page: https://github.com/openwhalereef/sanic-amqp
Author: Open Whalereef
Author-email: open@whalereef.com
License: BSD
Platform: any
Classifier: Environment :: Web Environment
Classifier: License :: OSI Approved :: BSD License
Classifier: Intended Audience :: Developers
Classifier: Programming Language :: Python
Classifier: Programming Language :: Python :: 3
Classifier: Programming Language :: Python :: 3.5
Classifier: Programming Language :: Python :: 3.6
Classifier: Programming Language :: Python :: 3.7
Classifier: Topic :: Software Development :: Libraries :: Python Modules
Requires-Dist: sanic-ext-base (==0.1.0)
Requires-Dist: aioamqp (==0.14.0)
